{
  "tag": "fear",
  "count": 21,
  "quotes": [
    {
      "text": "Pitching is the art of instilling fear.",
      "author": "Sandy Koufax",
      "source": "quotable.io",
      "tags": [
        "fear"
      ]
    },
    {
      "text": "Listen to what you know instead of what you fear.",
      "author": "Richard Bach",
      "source": "quotable.io",
      "tags": [
        "fear"
      ]
    },
    {
      "text": "As we are liberated from our own fear, our presence automatically liberates others.",
      "author": "Nelson Mandela",
      "source": "quotable.io",
      "tags": [
        "fear"
      ]
    },
    {
      "text": "Fear grows in darkness; if you think there's a bogeyman around, turn on the light.",
      "author": "Dorothy Thompson",
      "source": "quotable.io",
      "tags": [
        "fear"
      ]
    },
    {
      "text": "The free man is he who does not fear to go to the end of his thought.",
      "author": "Léon Blum",
      "source": "quotable.io",
      "tags": [
        "fear"
      ]
    },
    {
      "text": "Nothing could be worse than the fear that one had given up too soon and left one unexpended effort that might have saved the world.",
      "author": "Jane Addams",
      "source": "quotable.io",
      "tags": [
        "fear"
      ]
    },
    {
      "text": "Nothing in life is to be feared, it is only to be understood. Now is the time to understand more, so that we may fear less.",
      "author": "Marie Curie",
      "source": "quotable.io",
      "tags": [
        "fear"
      ]
    },
    {
      "text": "Nothing diminishes anxiety faster than action.",
      "author": "Walter Inglis Anderson",
      "source": "quotable.io",
      "tags": [
        "fear"
      ]
    },
    {
      "text": "Fear is your worst enemy. Risk is your best friend.",
      "author": "Gurbaksh Chahal",
      "source": "zenquotes.io",
      "tags": [
        "fear"
      ]
    },
    {
      "text": "You gain strength, courage and confidence by every experience in which you really stop to look fear in the face.",
      "author": "Eleanor Roosevelt",
      "source": "zenquotes.io",
      "tags": [
        "fear"
      ]
    },
    {
      "text": "The only thing we have to fear is fear itself.",
      "author": "Franklin D. Roosevelt",
      "source": "zenquotes.io",
      "tags": [
        "fear"
      ]
    },
    {
      "text": "A fear of weakness only strengthens weakness.",
      "author": "Criss Jami",
      "source": "zenquotes.io",
      "tags": [
        "fear"
      ]
    },
    {
      "text": "What you are afraid of is never as bad as what you imagine. The fear you let build up in your mind is worse than the situation that actually exists.",
      "author": "Spencer Johnson",
      "source": "zenquotes.io",
      "tags": [
        "fear"
      ]
    },
    {
      "text": "Don't be pushed around by the fears in your mind. Be led by the dreams in your heart.",
      "author": "Roy T. Bennett",
      "source": "zenquotes.io",
      "tags": [
        "fear"
      ]
    },
    {
      "text": "Hope and fear come from feeling that we lack something; they come from a sense of poverty.",
      "author": "Pema Chodron",
      "source": "zenquotes.io",
      "tags": [
        "fear"
      ]
    },
    {
      "text": "I never worry about action, but only inaction.",
      "author": "Winston Churchill",
      "source": "quotable.io",
      "tags": [
        "fear"
      ]
    },
    {
      "text": "A day of worry is more exhausting than a day of work.",
      "author": "John Lubbock",
      "source": "quotable.io",
      "tags": [
        "fear"
      ]
    },
    {
      "text": "Do not worry about your difficulties in Mathematics. I can assure you mine are still greater.",
      "author": "Albert Einstein",
      "source": "quotable.io",
      "tags": [
        "fear"
      ]
    },
    {
      "text": "Don't worry about people stealing your ideas. If your ideas are any good, you'll have to ram them down people's throats.",
      "author": "Howard H. Aiken",
      "source": "quotable.io",
      "tags": [
        "fear"
      ]
    },
    {
      "text": "Man should fear never beginning to live.",
      "author": "Marcus Aurelius",
      "source": "zenquotes.io",
      "tags": [
        "fear"
      ]
    },
    {
      "text": "Have the fearless attitude of a hero and the loving heart of a child.",
      "author": "Soyen Shaku",
      "source": "zenquotes.io",
      "tags": [
        "fear"
      ]
    }
  ]
}